posenet
