Metadata-Version: 1.0
Name: posenet
Version: 0.0.3
Summary: Extract pose vertex data from images
Home-page: https://github.com/yaledhlab/posenet
Author: Douglas Duhaime
Author-email: douglas.duhaime@gmail.com
License: MIT
Keywords: machine-vision,computer-vision,image-processing,data-collection
Platform: UNKNOWN
